django_error_skins/__init__.py
django_error_skins/admin.py
django_error_skins/apps.py
django_error_skins/context_processors/settings.py
django_error_skins/migrations/0001_initial.py
django_error_skins/migrations/0002_allauthskin_logo.py
django_error_skins/migrations/0003_allauthskin_background_image.py
django_error_skins/migrations/0004_allauthskin_font.py
django_error_skins/migrations/__init__.py
django_error_skins/models.py
django_error_skins/static/allauth_skins/css/.gitkeep
django_error_skins/static/allauth_skins/css/allauth_skins.css
django_error_skins/static/allauth_skins/css/allauth_skins.js
django_error_skins/static/allauth_skins/css/login.css
django_error_skins/static/allauth_skins/css/login.js
django_error_skins/static/allauth_skins/css/main.css
django_error_skins/static/allauth_skins/css/main.js
django_error_skins/static/allauth_skins/images/.gitkeep
django_error_skins/static/allauth_skins/images/default/facebook.svg
django_error_skins/static/allauth_skins/images/default/github.svg
django_error_skins/static/allauth_skins/images/default/google.svg
django_error_skins/static/allauth_skins/images/default/linkedin.svg
django_error_skins/static/allauth_skins/js/.gitkeep
django_error_skins/static/allauth_skins/sass/_base.scss
django_error_skins/static/allauth_skins/sass/_form.scss
django_error_skins/static/allauth_skins/sass/_info_page.scss
django_error_skins/static/allauth_skins/sass/_main.scss
django_error_skins/static/allauth_skins/sass/_variables.scss
django_error_skins/static/allauth_skins/sass/abstracts/_utilities.scss
django_error_skins/static/allauth_skins/sass/base/_reset.scss
django_error_skins/static/allauth_skins/sass/components/_button.scss
django_error_skins/static/allauth_skins/sass/components/_container.scss
django_error_skins/static/allauth_skins/sass/components/_hr.scss
django_error_skins/static/allauth_skins/sass/components/_input.scss
django_error_skins/static/allauth_skins/sass/components/_logo.scss
django_error_skins-0.1.0.dist-info/LICENSE
django_error_skins-0.1.0.dist-info/WHEEL
django_error_skins-0.1.0.dist-info/METADATA
django_error_skins-0.1.0.dist-info/RECORD
